{
  "required": true,
  "package": "com.yummy.naraka.mixin",
  "compatibilityLevel": "JAVA_21",
  "minVersion": "0.8",
  "client": [
    "client.CameraMixin",
    "client.DripParticleMixin",
    "client.EntityRenderDispatcherMixin",
    "client.FogRendererMixin",
    "client.HiddenOreRendererMixin",
    "client.ItemBlockRenderTypesMixin",
    "client.ItemEntityRendererMixin",
    "client.ItemModelResolverMixin",
    "client.ItemRendererMixin",
    "client.ItemStackMixin",
    "client.LocalPlayerMixin",
    "client.MinecraftMixin",
    "client.MouseHandlerMixin",
    "client.ScreenEffectRendererMixin",
    "client.SimpleSoundInstanceMixin"
  ],
  "mixins": [
    "FeatureMixin",
    "HerobrineTotemActivatingItemMixin",
    "LivingEntityMixin",
    "PlayerListMixin",
    "PlayerMixin",
    "ServerEntityMixin",
    "ServerPlayerGameModeMixin",
    "WanderingTraderMixin",
    "accessor.CreativeModeTabsAccessor",
    "invoker.MangroveRootsBlockInvoker",
    "invoker.MobEffectInvoker",
    "invoker.RootPlacerTypeInvoker"
  ],
  "injectors": {
    "defaultRequire": 1
  }
}
